pytest_attempt_summary/__init__.py
pytest_attempt_summary/attempt_diff.py
pytest_attempt_summary/attempt_summary.py
pytest_attempt_summary/attempt_view.py
pytest_attempt_summary/failure_panel.py
pytest_attempt_summary/plugin.py
pytest_attempt_summary/retry_insight.py
pytest_attempt_summary/scripts/attempt_summary.js
pytest_attempt_summary/styles/attempt_summary.css
pytest_attempt_summary/templates/attempt_diff.html
pytest_attempt_summary/templates/attempt_summary.html
pytest_attempt_summary/templates/attempt_view_cards.html
pytest_attempt_summary/templates/attempt_view_chain.html
pytest_attempt_summary/templates/attempt_view_tabs.html
pytest_attempt_summary/templates/failure_panel.html
pytest_attempt_summary/templates/trace_block.html
pytest_attempt_summary/utils/__init__.py
pytest_attempt_summary/utils/template_loader.py
pytest_attempt_summary-0.1.2.dist-info/licenses/LICENSE
pytest_attempt_summary-0.1.2.dist-info/METADATA
pytest_attempt_summary-0.1.2.dist-info/WHEEL
pytest_attempt_summary-0.1.2.dist-info/entry_points.txt
pytest_attempt_summary-0.1.2.dist-info/top_level.txt
pytest_attempt_summary-0.1.2.dist-info/RECORD
