Metadata-Version: 2.4
Name: pytest-attempt-summary
Version: 0.1.2
Summary: Enhanced Allure Attempt Summary for Playwright + Pytest
Author-email: Hongxia He <hzz0214@outlook.com>
License: MIT License
Project-URL: Homepage, https://github.com/helingcai/pytest_attempt_summary
Project-URL: Repository, https://github.com/helingcai/pytest_attempt_summary
Classifier: Framework :: Pytest
Classifier: Programming Language :: Python :: 3
Classifier: License :: OSI Approved :: MIT License
Requires-Python: >=3.8
License-File: LICENSE
Requires-Dist: pytest>=7.0
Requires-Dist: allure-pytest>=2.13
Requires-Dist: playwright>=1.35
Dynamic: license-file
